Metadata-Version: 2.1
Name: comp-validator
Version: 0.1.0
Summary: BIDS-validator for computational data (simulations).
Home-page: https://github.com/dissagaliyeva/comp_bids
Author: Dinara Issagaliyeva
Author-email: dinarissaa@gmail.com
License: MIT license
Keywords: BIDS,validator,computational data
Platform: UNKNOWN
Classifier: Development Status :: 4 - Beta
Classifier: Intended Audience :: Science/Research
Classifier: Operating System :: Microsoft :: Windows :: Windows 11
Classifier: License :: OSI Approved :: MIT License
Classifier: Programming Language :: Python :: 3
Requires-Python: >=3.6
License-File: LICENSE
